setup.py
wbnn/__init__.py
wbnn/initializers.py
wbnn/layers.py
wbnn/optimizers.py
wbnn/wbnn.py
wbnn.egg-info/PKG-INFO
wbnn.egg-info/SOURCES.txt
wbnn.egg-info/dependency_links.txt
wbnn.egg-info/entry_points.txt
wbnn.egg-info/not-zip-safe
wbnn.egg-info/requires.txt
wbnn.egg-info/top_level.txt
wbnn/visualLogs/gui.py
wbnn/visualLogs/logger.py
wbnn/visualLogs/plot.py