Metadata-Version: 1.0
Name: wbnn
Version: 1.2.3
Summary: White Box Neural Networks. Neural Network and Deep Learning toolkit developed for educational purposes.
Home-page: https://github.com/develask/White-Box-Neural-Networks
Author: Mikel de Velasco Vázquez
Author-email: develascomikel@gmail.com
License: MIT
Project-URL: Documentation, https://github.com/develask/White-Box-Neural-Networks/wiki
Project-URL: Source Code, https://github.com/develask/White-Box-Neural-Networks
Platform: UNKNOWN
